difit/__init__.py
difit/__main__.py
difit/client/__init__.py
difit/client/parser.py
difit/client/run.py
difit/workflows/__init__.py
difit/workflows/dki.py
difit/workflows/dti.py
difit/workflows/inputnode.py
difit/workflows/bin/__init__.py
difit/workflows/bin/config.py
difit-1.0.dist-info/AUTHORS.rst
difit-1.0.dist-info/LICENSE.txt
difit-1.0.dist-info/METADATA
difit-1.0.dist-info/WHEEL
difit-1.0.dist-info/entry_points.txt
difit-1.0.dist-info/top_level.txt
difit-1.0.dist-info/RECORD
