Metadata-Version: 2.1
Name: difit
Version: 1.0
Summary: Diffusion weighted models fitting
Home-page: https://github.com/kodiweera/difit
Author: Chandana Kodiweera
Author-email: kodiweera@hotmail.com
License: MIT
Platform: any
Classifier: Development Status :: 5 - Production/Stable
Classifier: Programming Language :: Python
License-File: LICENSE.txt
License-File: AUTHORS.rst
Requires-Dist: sphinx (>=3.2.1)
Requires-Dist: nibabel
Requires-Dist: dipy
Requires-Dist: setuptools
Requires-Dist: pytest
Requires-Dist: tox
Requires-Dist: pytest-cov
Requires-Dist: numpy
Requires-Dist: twine
Requires-Dist: pydeps
Requires-Dist: fury
Requires-Dist: multiprocess
Requires-Dist: nipype
Requires-Dist: weasyprint
Requires-Dist: nilearn
Requires-Dist: importlib-metadata ; python_version < "3.8"
Provides-Extra: testing
Requires-Dist: setuptools ; extra == 'testing'
Requires-Dist: pytest ; extra == 'testing'
Requires-Dist: pytest-cov ; extra == 'testing'
